{
	"id": "14UAx110rmJrqlX",
	"json": "{\"id\":\"14UAx110rmJrqlX\",\"url\":\"https://doc.rust-lang.org/stable/core/arch/x86_64/constant._MM_CMPINT_EQ.html\",\"uniqueKey\":\"https://doc.rust-lang.org/stable/core/arch/x86_64/constant._MM_CMPINT_EQ.html\",\"method\":\"GET\",\"noRetry\":false,\"retryCount\":0,\"errorMessages\":[],\"headers\":{},\"userData\":{\"__crawlee\":{\"enqueueStrategy\":\"same-hostname\"}}}",
	"method": "GET",
	"orderNo": 1722144164029,
	"retryCount": 0,
	"uniqueKey": "https://doc.rust-lang.org/stable/core/arch/x86_64/constant._MM_CMPINT_EQ.html",
	"url": "https://doc.rust-lang.org/stable/core/arch/x86_64/constant._MM_CMPINT_EQ.html"
}