{
	"id": "1cjoxD5LmbEMGLJ",
	"json": "{\"id\":\"1cjoxD5LmbEMGLJ\",\"url\":\"https://doc.rust-lang.org/stable/reference/items/enumerations.html\",\"loadedUrl\":\"https://doc.rust-lang.org/stable/reference/items/enumerations.html\",\"uniqueKey\":\"https://doc.rust-lang.org/stable/reference/items/enumerations.html\",\"method\":\"GET\",\"noRetry\":false,\"retryCount\":0,\"errorMessages\":[],\"headers\":{},\"userData\":{\"__crawlee\":{\"enqueueStrategy\":\"same-hostname\",\"state\":4}},\"handledAt\":\"2024-07-28T05:12:52.944Z\"}",
	"method": "GET",
	"orderNo": null,
	"retryCount": 0,
	"uniqueKey": "https://doc.rust-lang.org/stable/reference/items/enumerations.html",
	"url": "https://doc.rust-lang.org/stable/reference/items/enumerations.html"
}