{
	"id": "1IuH0ePI5y73fb7",
	"json": "{\"id\":\"1IuH0ePI5y73fb7\",\"url\":\"https://doc.rust-lang.org/stable/core/arch/x86/fn._mm256_maskz_min_epu8.html\",\"uniqueKey\":\"https://doc.rust-lang.org/stable/core/arch/x86/fn._mm256_maskz_min_epu8.html\",\"method\":\"GET\",\"noRetry\":false,\"retryCount\":0,\"errorMessages\":[],\"headers\":{},\"userData\":{\"__crawlee\":{\"enqueueStrategy\":\"same-hostname\"}}}",
	"method": "GET",
	"orderNo": 1722144166373,
	"retryCount": 0,
	"uniqueKey": "https://doc.rust-lang.org/stable/core/arch/x86/fn._mm256_maskz_min_epu8.html",
	"url": "https://doc.rust-lang.org/stable/core/arch/x86/fn._mm256_maskz_min_epu8.html"
}