{
	"id": "5yfzVLFLbuCbBoN",
	"json": "{\"id\":\"5yfzVLFLbuCbBoN\",\"url\":\"https://doc.rust-lang.org/stable/core/arch/x86_64/fn._mm256_popcnt_epi32.html\",\"uniqueKey\":\"https://doc.rust-lang.org/stable/core/arch/x86_64/fn._mm256_popcnt_epi32.html\",\"method\":\"GET\",\"noRetry\":false,\"retryCount\":0,\"errorMessages\":[],\"headers\":{},\"userData\":{\"__crawlee\":{\"enqueueStrategy\":\"same-hostname\"}}}",
	"method": "GET",
	"orderNo": 1722144166518,
	"retryCount": 0,
	"uniqueKey": "https://doc.rust-lang.org/stable/core/arch/x86_64/fn._mm256_popcnt_epi32.html",
	"url": "https://doc.rust-lang.org/stable/core/arch/x86_64/fn._mm256_popcnt_epi32.html"
}