{
	"id": "bT6nuNHgoGu92Lt",
	"json": "{\"id\":\"bT6nuNHgoGu92Lt\",\"url\":\"https://doc.rust-lang.org/stable/core/arch/arm/fn.vsri_n_u16.html\",\"uniqueKey\":\"https://doc.rust-lang.org/stable/core/arch/arm/fn.vsri_n_u16.html\",\"method\":\"GET\",\"noRetry\":false,\"retryCount\":0,\"errorMessages\":[],\"headers\":{},\"userData\":{\"__crawlee\":{\"enqueueStrategy\":\"same-hostname\"}}}",
	"method": "GET",
	"orderNo": 1722144166624,
	"retryCount": 0,
	"uniqueKey": "https://doc.rust-lang.org/stable/core/arch/arm/fn.vsri_n_u16.html",
	"url": "https://doc.rust-lang.org/stable/core/arch/arm/fn.vsri_n_u16.html"
}