{
	"id": "buY1LPGN2P7I2us",
	"json": "{\"id\":\"buY1LPGN2P7I2us\",\"url\":\"https://doc.rust-lang.org/rustc/platform-support/hurd.html\",\"uniqueKey\":\"https://doc.rust-lang.org/rustc/platform-support/hurd.html\",\"method\":\"GET\",\"noRetry\":false,\"retryCount\":0,\"errorMessages\":[],\"headers\":{},\"userData\":{\"__crawlee\":{\"enqueueStrategy\":\"same-hostname\"}}}",
	"method": "GET",
	"orderNo": 1722143681584,
	"retryCount": 0,
	"uniqueKey": "https://doc.rust-lang.org/rustc/platform-support/hurd.html",
	"url": "https://doc.rust-lang.org/rustc/platform-support/hurd.html"
}