{
	"id": "cdV3kgcUVpmB6jr",
	"json": "{\"id\":\"cdV3kgcUVpmB6jr\",\"url\":\"https://doc.rust-lang.org/stable/error_codes/E0520.html\",\"uniqueKey\":\"https://doc.rust-lang.org/stable/error_codes/E0520.html\",\"method\":\"GET\",\"noRetry\":false,\"retryCount\":0,\"errorMessages\":[],\"headers\":{},\"userData\":{\"__crawlee\":{\"enqueueStrategy\":\"same-hostname\"}}}",
	"method": "GET",
	"orderNo": 1722143587038,
	"retryCount": 0,
	"uniqueKey": "https://doc.rust-lang.org/stable/error_codes/E0520.html",
	"url": "https://doc.rust-lang.org/stable/error_codes/E0520.html"
}