{
	"id": "dMc1hAVhSLI1u7n",
	"json": "{\"id\":\"dMc1hAVhSLI1u7n\",\"url\":\"https://doc.rust-lang.org/stable/error_codes/E0429.html\",\"uniqueKey\":\"https://doc.rust-lang.org/stable/error_codes/E0429.html\",\"method\":\"GET\",\"noRetry\":false,\"retryCount\":0,\"errorMessages\":[],\"headers\":{},\"userData\":{\"__crawlee\":{\"enqueueStrategy\":\"same-hostname\"}}}",
	"method": "GET",
	"orderNo": 1722143587008,
	"retryCount": 0,
	"uniqueKey": "https://doc.rust-lang.org/stable/error_codes/E0429.html",
	"url": "https://doc.rust-lang.org/stable/error_codes/E0429.html"
}