{
	"id": "FE8omjywNvSDMml",
	"json": "{\"id\":\"FE8omjywNvSDMml\",\"url\":\"https://doc.rust-lang.org/stable/core/arch/x86_64/fn._mm256_maskz_unpacklo_ps.html\",\"uniqueKey\":\"https://doc.rust-lang.org/stable/core/arch/x86_64/fn._mm256_maskz_unpacklo_ps.html\",\"method\":\"GET\",\"noRetry\":false,\"retryCount\":0,\"errorMessages\":[],\"headers\":{},\"userData\":{\"__crawlee\":{\"enqueueStrategy\":\"same-hostname\"}}}",
	"method": "GET",
	"orderNo": 1722144166504,
	"retryCount": 0,
	"uniqueKey": "https://doc.rust-lang.org/stable/core/arch/x86_64/fn._mm256_maskz_unpacklo_ps.html",
	"url": "https://doc.rust-lang.org/stable/core/arch/x86_64/fn._mm256_maskz_unpacklo_ps.html"
}