{
	"id": "k2mK4AcXT0j2JY0",
	"json": "{\"id\":\"k2mK4AcXT0j2JY0\",\"url\":\"https://doc.rust-lang.org/stable/core/panic/struct.Location.html\",\"uniqueKey\":\"https://doc.rust-lang.org/stable/core/panic/struct.Location.html\",\"method\":\"GET\",\"noRetry\":false,\"retryCount\":0,\"errorMessages\":[],\"headers\":{},\"userData\":{\"__crawlee\":{\"enqueueStrategy\":\"same-hostname\"}}}",
	"method": "GET",
	"orderNo": 1722143580764,
	"retryCount": 0,
	"uniqueKey": "https://doc.rust-lang.org/stable/core/panic/struct.Location.html",
	"url": "https://doc.rust-lang.org/stable/core/panic/struct.Location.html"
}