{
	"id": "KyPudci0AIhv8yK",
	"json": "{\"id\":\"KyPudci0AIhv8yK\",\"url\":\"https://doc.rust-lang.org/stable/std/intrinsics/simd/fn.simd_ctlz.html\",\"loadedUrl\":\"https://doc.rust-lang.org/stable/std/intrinsics/simd/fn.simd_ctlz.html\",\"uniqueKey\":\"https://doc.rust-lang.org/stable/std/intrinsics/simd/fn.simd_ctlz.html\",\"method\":\"GET\",\"noRetry\":false,\"retryCount\":0,\"errorMessages\":[],\"headers\":{},\"userData\":{\"__crawlee\":{\"enqueueStrategy\":\"same-hostname\",\"state\":4}},\"handledAt\":\"2024-07-28T05:26:43.964Z\"}",
	"method": "GET",
	"orderNo": null,
	"retryCount": 0,
	"uniqueKey": "https://doc.rust-lang.org/stable/std/intrinsics/simd/fn.simd_ctlz.html",
	"url": "https://doc.rust-lang.org/stable/std/intrinsics/simd/fn.simd_ctlz.html"
}