{
	"id": "lADphlr38zlOTJN",
	"json": "{\"id\":\"lADphlr38zlOTJN\",\"url\":\"https://doc.rust-lang.org/stable/reference/expressions.html\",\"loadedUrl\":\"https://doc.rust-lang.org/stable/reference/expressions.html\",\"uniqueKey\":\"https://doc.rust-lang.org/stable/reference/expressions.html\",\"method\":\"GET\",\"noRetry\":false,\"retryCount\":0,\"errorMessages\":[],\"headers\":{},\"userData\":{\"__crawlee\":{\"enqueueStrategy\":\"same-hostname\",\"state\":4}},\"handledAt\":\"2024-07-28T05:13:04.313Z\"}",
	"method": "GET",
	"orderNo": null,
	"retryCount": 0,
	"uniqueKey": "https://doc.rust-lang.org/stable/reference/expressions.html",
	"url": "https://doc.rust-lang.org/stable/reference/expressions.html"
}