{
	"id": "LrpYMM7amsfKj3b",
	"json": "{\"id\":\"LrpYMM7amsfKj3b\",\"url\":\"https://doc.rust-lang.org/1.80.0/src/core/portable-simd/crates/core_simd/src/to_bytes.rs.html\",\"uniqueKey\":\"https://doc.rust-lang.org/1.80.0/src/core/portable-simd/crates/core_simd/src/to_bytes.rs.html\",\"method\":\"GET\",\"noRetry\":false,\"retryCount\":0,\"errorMessages\":[],\"headers\":{},\"userData\":{\"__crawlee\":{\"enqueueStrategy\":\"same-hostname\"}}}",
	"method": "GET",
	"orderNo": 1722143511723,
	"retryCount": 0,
	"uniqueKey": "https://doc.rust-lang.org/1.80.0/src/core/portable-simd/crates/core_simd/src/to_bytes.rs.html",
	"url": "https://doc.rust-lang.org/1.80.0/src/core/portable-simd/crates/core_simd/src/to_bytes.rs.html"
}