{
	"id": "M127wQy2VsqV8x4",
	"json": "{\"id\":\"M127wQy2VsqV8x4\",\"url\":\"https://doc.rust-lang.org/stable/core/arch/x86_64/fn._mm_mask_load_ps.html\",\"uniqueKey\":\"https://doc.rust-lang.org/stable/core/arch/x86_64/fn._mm_mask_load_ps.html\",\"method\":\"GET\",\"noRetry\":false,\"retryCount\":0,\"errorMessages\":[],\"headers\":{},\"userData\":{\"__crawlee\":{\"enqueueStrategy\":\"same-hostname\"}}}",
	"method": "GET",
	"orderNo": 1722144170093,
	"retryCount": 0,
	"uniqueKey": "https://doc.rust-lang.org/stable/core/arch/x86_64/fn._mm_mask_load_ps.html",
	"url": "https://doc.rust-lang.org/stable/core/arch/x86_64/fn._mm_mask_load_ps.html"
}