{
	"id": "R76Kq5X9Igr4StH",
	"json": "{\"id\":\"R76Kq5X9Igr4StH\",\"url\":\"https://doc.rust-lang.org/unstable-book/library-features/edition-panic.html\",\"uniqueKey\":\"https://doc.rust-lang.org/unstable-book/library-features/edition-panic.html\",\"method\":\"GET\",\"noRetry\":false,\"retryCount\":0,\"errorMessages\":[],\"headers\":{},\"userData\":{\"__crawlee\":{\"enqueueStrategy\":\"same-hostname\"}}}",
	"method": "GET",
	"orderNo": 1722144037747,
	"retryCount": 0,
	"uniqueKey": "https://doc.rust-lang.org/unstable-book/library-features/edition-panic.html",
	"url": "https://doc.rust-lang.org/unstable-book/library-features/edition-panic.html"
}