{
	"id": "RtkDq3p4hUdHMgu",
	"json": "{\"id\":\"RtkDq3p4hUdHMgu\",\"url\":\"https://doc.rust-lang.org/1.80.0/src/core/stdarch/crates/core_arch/src/riscv32/mod.rs.html\",\"uniqueKey\":\"https://doc.rust-lang.org/1.80.0/src/core/stdarch/crates/core_arch/src/riscv32/mod.rs.html\",\"method\":\"GET\",\"noRetry\":false,\"retryCount\":0,\"errorMessages\":[],\"headers\":{},\"userData\":{\"__crawlee\":{\"enqueueStrategy\":\"same-hostname\"}}}",
	"method": "GET",
	"orderNo": 1722143511743,
	"retryCount": 0,
	"uniqueKey": "https://doc.rust-lang.org/1.80.0/src/core/stdarch/crates/core_arch/src/riscv32/mod.rs.html",
	"url": "https://doc.rust-lang.org/1.80.0/src/core/stdarch/crates/core_arch/src/riscv32/mod.rs.html"
}