{
	"id": "snZ6eAcpwoO8CTM",
	"json": "{\"id\":\"snZ6eAcpwoO8CTM\",\"url\":\"https://doc.rust-lang.org/stable/core/arch/x86/constant._MM_PERM_ADBC.html\",\"uniqueKey\":\"https://doc.rust-lang.org/stable/core/arch/x86/constant._MM_PERM_ADBC.html\",\"method\":\"GET\",\"noRetry\":false,\"retryCount\":0,\"errorMessages\":[],\"headers\":{},\"userData\":{\"__crawlee\":{\"enqueueStrategy\":\"same-hostname\"}}}",
	"method": "GET",
	"orderNo": 1722144164061,
	"retryCount": 0,
	"uniqueKey": "https://doc.rust-lang.org/stable/core/arch/x86/constant._MM_PERM_ADBC.html",
	"url": "https://doc.rust-lang.org/stable/core/arch/x86/constant._MM_PERM_ADBC.html"
}