{
	"id": "SoFGm8GfXcJ1yWM",
	"json": "{\"id\":\"SoFGm8GfXcJ1yWM\",\"url\":\"https://doc.rust-lang.org/stable/reference/type-coercions.html\",\"loadedUrl\":\"https://doc.rust-lang.org/stable/reference/type-coercions.html\",\"uniqueKey\":\"https://doc.rust-lang.org/stable/reference/type-coercions.html\",\"method\":\"GET\",\"noRetry\":false,\"retryCount\":0,\"errorMessages\":[],\"headers\":{},\"userData\":{\"__crawlee\":{\"enqueueStrategy\":\"same-hostname\",\"state\":4}},\"handledAt\":\"2024-07-28T05:13:30.250Z\"}",
	"method": "GET",
	"orderNo": null,
	"retryCount": 0,
	"uniqueKey": "https://doc.rust-lang.org/stable/reference/type-coercions.html",
	"url": "https://doc.rust-lang.org/stable/reference/type-coercions.html"
}