{
	"id": "SyoEgMsLaAPlrpF",
	"json": "{\"id\":\"SyoEgMsLaAPlrpF\",\"url\":\"https://doc.rust-lang.org/stable/std/simd/type.f64x2.html\",\"loadedUrl\":\"https://doc.rust-lang.org/stable/std/simd/type.f64x2.html\",\"uniqueKey\":\"https://doc.rust-lang.org/stable/std/simd/type.f64x2.html\",\"method\":\"GET\",\"noRetry\":false,\"retryCount\":0,\"errorMessages\":[],\"headers\":{},\"userData\":{\"__crawlee\":{\"enqueueStrategy\":\"same-hostname\",\"state\":4}},\"handledAt\":\"2024-07-28T05:24:35.018Z\"}",
	"method": "GET",
	"orderNo": null,
	"retryCount": 0,
	"uniqueKey": "https://doc.rust-lang.org/stable/std/simd/type.f64x2.html",
	"url": "https://doc.rust-lang.org/stable/std/simd/type.f64x2.html"
}