{
	"id": "trxa39T0uSA3mOC",
	"json": "{\"id\":\"trxa39T0uSA3mOC\",\"url\":\"https://doc.rust-lang.org/1.80.0/src/std/os/unix/net/ancillary.rs.html\",\"uniqueKey\":\"https://doc.rust-lang.org/1.80.0/src/std/os/unix/net/ancillary.rs.html\",\"method\":\"GET\",\"noRetry\":false,\"retryCount\":0,\"errorMessages\":[],\"headers\":{},\"userData\":{\"__crawlee\":{\"enqueueStrategy\":\"same-hostname\"}}}",
	"method": "GET",
	"orderNo": 1722143512325,
	"retryCount": 0,
	"uniqueKey": "https://doc.rust-lang.org/1.80.0/src/std/os/unix/net/ancillary.rs.html",
	"url": "https://doc.rust-lang.org/1.80.0/src/std/os/unix/net/ancillary.rs.html"
}