{
	"id": "VFa9kYweeJmbc7o",
	"json": "{\"id\":\"VFa9kYweeJmbc7o\",\"url\":\"https://doc.rust-lang.org/stable/core/arch/wasm32/fn.i8x16_sub.html\",\"uniqueKey\":\"https://doc.rust-lang.org/stable/core/arch/wasm32/fn.i8x16_sub.html\",\"method\":\"GET\",\"noRetry\":false,\"retryCount\":0,\"errorMessages\":[],\"headers\":{},\"userData\":{\"__crawlee\":{\"enqueueStrategy\":\"same-hostname\"}}}",
	"method": "GET",
	"orderNo": 1722144165976,
	"retryCount": 0,
	"uniqueKey": "https://doc.rust-lang.org/stable/core/arch/wasm32/fn.i8x16_sub.html",
	"url": "https://doc.rust-lang.org/stable/core/arch/wasm32/fn.i8x16_sub.html"
}