{
	"id": "WAjzN439K0Xp4cj",
	"json": "{\"id\":\"WAjzN439K0Xp4cj\",\"url\":\"https://doc.rust-lang.org/stable/core/arch/x86_64/constant._CMP_LE_OQ.html\",\"uniqueKey\":\"https://doc.rust-lang.org/stable/core/arch/x86_64/constant._CMP_LE_OQ.html\",\"method\":\"GET\",\"noRetry\":false,\"retryCount\":0,\"errorMessages\":[],\"headers\":{},\"userData\":{\"__crawlee\":{\"enqueueStrategy\":\"same-hostname\"}}}",
	"method": "GET",
	"orderNo": 1722144163956,
	"retryCount": 0,
	"uniqueKey": "https://doc.rust-lang.org/stable/core/arch/x86_64/constant._CMP_LE_OQ.html",
	"url": "https://doc.rust-lang.org/stable/core/arch/x86_64/constant._CMP_LE_OQ.html"
}