{
	"id": "wDDTlJO1mNsd9ki",
	"json": "{\"id\":\"wDDTlJO1mNsd9ki\",\"url\":\"https://doc.rust-lang.org/stable/core/arch/wasm32/fn.i8x16_all_true.html\",\"uniqueKey\":\"https://doc.rust-lang.org/stable/core/arch/wasm32/fn.i8x16_all_true.html\",\"method\":\"GET\",\"noRetry\":false,\"retryCount\":0,\"errorMessages\":[],\"headers\":{},\"userData\":{\"__crawlee\":{\"enqueueStrategy\":\"same-hostname\"}}}",
	"method": "GET",
	"orderNo": 1722144165967,
	"retryCount": 0,
	"uniqueKey": "https://doc.rust-lang.org/stable/core/arch/wasm32/fn.i8x16_all_true.html",
	"url": "https://doc.rust-lang.org/stable/core/arch/wasm32/fn.i8x16_all_true.html"
}