{
	"id": "x5GEZAFivgSLNa7",
	"json": "{\"id\":\"x5GEZAFivgSLNa7\",\"url\":\"https://doc.rust-lang.org/stable/core/arch/x86/constant._MM_PERM_ABCD.html\",\"uniqueKey\":\"https://doc.rust-lang.org/stable/core/arch/x86/constant._MM_PERM_ABCD.html\",\"method\":\"GET\",\"noRetry\":false,\"retryCount\":0,\"errorMessages\":[],\"headers\":{},\"userData\":{\"__crawlee\":{\"enqueueStrategy\":\"same-hostname\"}}}",
	"method": "GET",
	"orderNo": 1722144164049,
	"retryCount": 0,
	"uniqueKey": "https://doc.rust-lang.org/stable/core/arch/x86/constant._MM_PERM_ABCD.html",
	"url": "https://doc.rust-lang.org/stable/core/arch/x86/constant._MM_PERM_ABCD.html"
}