{
	"id": "YRHEdz4LYzxKlYp",
	"json": "{\"id\":\"YRHEdz4LYzxKlYp\",\"url\":\"https://doc.rust-lang.org/rust-by-example/error/option_unwrap.html\",\"uniqueKey\":\"https://doc.rust-lang.org/rust-by-example/error/option_unwrap.html\",\"method\":\"GET\",\"noRetry\":false,\"retryCount\":0,\"errorMessages\":[],\"headers\":{},\"userData\":{\"__crawlee\":{\"enqueueStrategy\":\"same-hostname\"}}}",
	"method": "GET",
	"orderNo": 1722144351202,
	"retryCount": 0,
	"uniqueKey": "https://doc.rust-lang.org/rust-by-example/error/option_unwrap.html",
	"url": "https://doc.rust-lang.org/rust-by-example/error/option_unwrap.html"
}