{
	"id": "zn7LSHmrGzjBKfY",
	"json": "{\"id\":\"zn7LSHmrGzjBKfY\",\"url\":\"https://doc.rust-lang.org/1.80.0/src/core/future/poll_fn.rs.html#133\",\"uniqueKey\":\"https://doc.rust-lang.org/1.80.0/src/core/future/poll_fn.rs.html\",\"method\":\"GET\",\"noRetry\":false,\"retryCount\":0,\"errorMessages\":[],\"headers\":{},\"userData\":{\"__crawlee\":{\"enqueueStrategy\":\"same-hostname\"}}}",
	"method": "GET",
	"orderNo": 1722143501109,
	"retryCount": 0,
	"uniqueKey": "https://doc.rust-lang.org/1.80.0/src/core/future/poll_fn.rs.html",
	"url": "https://doc.rust-lang.org/1.80.0/src/core/future/poll_fn.rs.html#133"
}